LICENSE
MANIFEST.in
README.md
setup.py
concerns/__init__.py
concerns/admin.py
concerns/forms.py
concerns/models.py
concerns/urls.py
concerns/views.py
concerns/migrations/0001_initial.py
concerns/migrations/0002_auto__add_field_concern_resolver.py
concerns/migrations/0003_auto__add_field_concern_headers.py
concerns/migrations/0004_auto__chg_field_concern_reporter.py
concerns/migrations/0005_auto__add_field_concern_ip.py
concerns/migrations/0006_auto__add_field_concern_resolved__chg_field_concern_created__chg_field.py
concerns/migrations/__init__.py
concerns/templates/concerns/concern_detail.html
concerns/templates/concerns/concern_email.txt
concerns/templates/concerns/concern_list.html
concerns/templates/concerns/report_concern.html
django_concerns.egg-info/PKG-INFO
django_concerns.egg-info/SOURCES.txt
django_concerns.egg-info/dependency_links.txt
django_concerns.egg-info/requires.txt
django_concerns.egg-info/top_level.txt