Metadata-Version: 1.0
Name: django-concerns
Version: 0.1.0
Summary: Django app for reporting privacy concerns
Home-page: https://github.com/cbmi/django-concerns/
Author: Byron Ruth
Author-email: b@devel.io
License: BSD
Keywords: PHI privacy concerns
Platform: UNKNOWN
Classifier: Development Status :: 5 - Production/Stable
Classifier: License :: OSI Approved :: BSD License
Classifier: Programming Language :: Python :: 2.6
Classifier: Programming Language :: Python :: 2.7
Classifier: Framework :: Django
Classifier: Topic :: Internet :: WWW/HTTP
Classifier: Intended Audience :: Developers
Classifier: Intended Audience :: Science/Research
Classifier: Intended Audience :: Healthcare Industry
Classifier: Intended Audience :: Information Technology
